{
  "stargazers": [
    {
      "login": "rosiereflo",
      "name": "",
      "email": "",
      "company": "",
      "bio": "",
      "location": "",
      "user_type": "User",
      "followers": 1,
      "public_repos": 0,
      "interaction_type": "star"
    },
    {
      "login": "MarianneSaugierRTE",
      "name": "Marianne Saugier",
      "email": "marianne.saugier@rte-france.com",
      "company": "RTE",
      "bio": "",
      "location": "France",
      "user_type": "User",
      "followers": 1,
      "public_repos": 0,
      "interaction_type": "star"
    },
    {
      "login": "petitrenaudseb",
      "name": "",
      "email": "",
      "company": "",
      "bio": "",
      "location": "",
      "user_type": "User",
      "followers": 0,
      "public_repos": 1,
      "interaction_type": "star"
    },
    {
      "login": "serge-inmost",
      "name": "Simon Gesret",
      "email": "",
      "company": "@Boralex-France ",
      "bio": "",
      "location": "Lyon, France",
      "user_type": "User",
      "followers": 3,
      "public_repos": 5,
      "interaction_type": "star"
    },
    {
      "login": "cuihantao",
      "name": "Hantao Cui",
      "email": "",
      "company": "North Carolina State University",
      "bio": "Associate Professor of Electrical and Computer Engineering. \r\n\r\nWe are bridging the power systems community with scientific computing.",
      "location": "Raleigh, NC",
      "user_type": "User",
      "followers": 242,
      "public_repos": 195,
      "interaction_type": "star"
    },
    {
      "login": "Neirda8282",
      "name": "",
      "email": "",
      "company": "",
      "bio": "",
      "location": "",
      "user_type": "User",
      "followers": 1,
      "public_repos": 30,
      "interaction_type": "star"
    },
    {
      "login": "rwl",
      "name": "Richard Lincoln",
      "email": "r.w.lincoln@gmail.com",
      "company": "",
      "bio": "Power Engineer",
      "location": "Berlin",
      "user_type": "User",
      "followers": 179,
      "public_repos": 186,
      "interaction_type": "star"
    },
    {
      "login": "milton-alvarenga",
      "name": "",
      "email": "",
      "company": "",
      "bio": "",
      "location": "",
      "user_type": "User",
      "followers": 30,
      "public_repos": 24,
      "interaction_type": "star"
    },
    {
      "login": "Oprax",
      "name": "Romain Muller",
      "email": "",
      "company": "",
      "bio": "",
      "location": "",
      "user_type": "User",
      "followers": 8,
      "public_repos": 27,
      "interaction_type": "star"
    },
    {
      "login": "RomainLosseauRTE",
      "name": "",
      "email": "",
      "company": "RTE",
      "bio": "",
      "location": "",
      "user_type": "User",
      "followers": 0,
      "public_repos": 0,
      "interaction_type": "star"
    },
    {
      "login": "whoiszyc",
      "name": "Yichen Zhang",
      "email": "",
      "company": "The University of Texas at Arlington",
      "bio": "Assistant Professor\r\nThe University of Texas at Arlington\r\nArlington, TX 76010, USA",
      "location": "416 Yates Street, Arlington, TX 76010, USA",
      "user_type": "User",
      "followers": 56,
      "public_repos": 98,
      "interaction_type": "star"
    },
    {
      "login": "pphuth",
      "name": "Philipp Huth",
      "email": "",
      "company": "",
      "bio": "",
      "location": "Germany",
      "user_type": "User",
      "followers": 46,
      "public_repos": 22,
      "interaction_type": "star"
    },
    {
      "login": "cybfr",
      "name": "",
      "email": "",
      "company": "",
      "bio": "",
      "location": "",
      "user_type": "User",
      "followers": 1,
      "public_repos": 23,
      "interaction_type": "star"
    },
    {
      "login": "syedyasserali",
      "name": "syed yasser ali",
      "email": "",
      "company": "FOSSEE, IIT Bombay",
      "bio": "PROJECT RESEARCH ASSOCIATE",
      "location": "mumbai",
      "user_type": "User",
      "followers": 1,
      "public_repos": 64,
      "interaction_type": "star"
    },
    {
      "login": "rsegur",
      "name": "Roman",
      "email": "",
      "company": "SuperGrid institute",
      "bio": "",
      "location": "Lyon",
      "user_type": "User",
      "followers": 1,
      "public_repos": 0,
      "interaction_type": "star"
    },
    {
      "login": "e2l-su",
      "name": "",
      "email": "",
      "company": "",
      "bio": "",
      "location": "",
      "user_type": "User",
      "followers": 0,
      "public_repos": 1,
      "interaction_type": "star"
    },
    {
      "login": "Sciemon",
      "name": "",
      "email": "",
      "company": "Fraunhofer IEE",
      "bio": "",
      "location": "Kassel, Germany",
      "user_type": "User",
      "followers": 6,
      "public_repos": 6,
      "interaction_type": "star"
    },
    {
      "login": "BDonnot",
      "name": "Benjamin DONNOT",
      "email": "",
      "company": "",
      "bio": "",
      "location": "",
      "user_type": "User",
      "followers": 50,
      "public_repos": 31,
      "interaction_type": "star"
    },
    {
      "login": "renonat",
      "name": "Reno Natalizio",
      "email": "",
      "company": "Opus One Solutions",
      "bio": "",
      "location": "Canada",
      "user_type": "User",
      "followers": 6,
      "public_repos": 5,
      "interaction_type": "star"
    },
    {
      "login": "songshaofeng",
      "name": "",
      "email": "",
      "company": "",
      "bio": "",
      "location": "",
      "user_type": "User",
      "followers": 0,
      "public_repos": 6,
      "interaction_type": "star"
    },
    {
      "login": "aicccode",
      "name": "aicc",
      "email": "gooqle.com.hk@gmail.com",
      "company": "aicc.site",
      "bio": "Less is more and keep it simple and stupid.",
      "location": "GZ.CN",
      "user_type": "User",
      "followers": 5,
      "public_repos": 136,
      "interaction_type": "star"
    },
    {
      "login": "piliadis",
      "name": "",
      "email": "",
      "company": "",
      "bio": "",
      "location": "",
      "user_type": "User",
      "followers": 1,
      "public_repos": 1,
      "interaction_type": "star"
    },
    {
      "login": "sorrento",
      "name": "",
      "email": "",
      "company": "",
      "bio": "",
      "location": "",
      "user_type": "User",
      "followers": 0,
      "public_repos": 27,
      "interaction_type": "star"
    },
    {
      "login": "metab0t",
      "name": "Yue Yang",
      "email": "",
      "company": "Hefei University of Technology",
      "bio": "Academic researcher interested in \r\noptimization of power system",
      "location": "China",
      "user_type": "User",
      "followers": 80,
      "public_repos": 64,
      "interaction_type": "star"
    },
    {
      "login": "lucassm",
      "name": "Lucas Melo",
      "email": "lucas.silveiramelo@gmail.com",
      "company": "Federal University of Ceara",
      "bio": "Associate Professor at Electrical Engineering Department - Federal University of Ceara - Brazil",
      "location": "Fortaleza, Ce - Brazil",
      "user_type": "User",
      "followers": 46,
      "public_repos": 63,
      "interaction_type": "star"
    },
    {
      "login": "traversaro",
      "name": "Silvio Traversaro",
      "email": "",
      "company": "Italian Institute of Technology",
      "bio": "If you mentioned me and I did not reply in the last 72h, probably I lost the message somehow, so please ping me, thanks!\r\n",
      "location": "Genoa",
      "user_type": "User",
      "followers": 467,
      "public_repos": 762,
      "interaction_type": "star"
    },
    {
      "login": "thorade",
      "name": "Matthis Thorade",
      "email": "matthis.thorade@modelon.com",
      "company": "@modelon",
      "bio": "",
      "location": "",
      "user_type": "User",
      "followers": 61,
      "public_repos": 14,
      "interaction_type": "star"
    },
    {
      "login": "GGiraudG",
      "name": "Guillaume",
      "email": "",
      "company": "@RTE",
      "bio": "",
      "location": "",
      "user_type": "User",
      "followers": 0,
      "public_repos": 0,
      "interaction_type": "star"
    },
    {
      "login": "gautierbureau",
      "name": "Gautier Bureau",
      "email": "gautier.bureau@gmail.com",
      "company": "@dynawo ",
      "bio": "",
      "location": "France",
      "user_type": "User",
      "followers": 2,
      "public_repos": 37,
      "interaction_type": "star"
    },
    {
      "login": "yayima",
      "name": "Edward Zhang",
      "email": "",
      "company": "",
      "bio": "",
      "location": "Beijing",
      "user_type": "User",
      "followers": 18,
      "public_repos": 12,
      "interaction_type": "star"
    },
    {
      "login": "sylvlecl",
      "name": "Sylvain Leclerc",
      "email": "sylvain.leclerc@rte-france.com",
      "company": "RTE",
      "bio": "Software engineer at RTE, with a strong interest in energy sector, computations, and applied mathematics.",
      "location": "Paris",
      "user_type": "User",
      "followers": 5,
      "public_repos": 5,
      "interaction_type": "star"
    },
    {
      "login": "MV564",
      "name": "Jose Martin",
      "email": "",
      "company": "IIUNAM",
      "bio": "PhD Candidate at Institute of Engineering, UNAM",
      "location": "Mexico",
      "user_type": "User",
      "followers": 0,
      "public_repos": 0,
      "interaction_type": "star"
    },
    {
      "login": "gnakti",
      "name": "",
      "email": "",
      "company": "",
      "bio": "",
      "location": "",
      "user_type": "User",
      "followers": 3,
      "public_repos": 5,
      "interaction_type": "star"
    },
    {
      "login": "MachinesOnTheRise",
      "name": "RiseOfTheMachines",
      "email": "",
      "company": "",
      "bio": "",
      "location": "Austin, Tx",
      "user_type": "User",
      "followers": 0,
      "public_repos": 0,
      "interaction_type": "star"
    },
    {
      "login": "sifatron",
      "name": "Sifat Shahriar Khan",
      "email": "sifat.torque@gmail.com",
      "company": "EnerSys",
      "bio": "AI and Machine Learning Lead at EnerSys | Experienced Embedded Firmware Developer",
      "location": "Reading, PA",
      "user_type": "User",
      "followers": 4,
      "public_repos": 66,
      "interaction_type": "star"
    },
    {
      "login": "jiedxu",
      "name": "Jie (Edward) Xu",
      "email": "edxu96@outlook.com",
      "company": "House of Energy Markets and Finance, University Duisburg-Essen",
      "bio": "Math simulation/optimization, graph theory and dynamic procurement & pricing for energy systems, food supplies, retailing, etc.",
      "location": "Essen, Germany",
      "user_type": "User",
      "followers": 94,
      "public_repos": 20,
      "interaction_type": "star"
    },
    {
      "login": "BenoitJeanson",
      "name": "Beno\u00eet Jeanson",
      "email": "",
      "company": "RTE",
      "bio": "",
      "location": "Paris",
      "user_type": "User",
      "followers": 0,
      "public_repos": 10,
      "interaction_type": "star"
    },
    {
      "login": "martinmoraga",
      "name": "Martin Moraga",
      "email": "",
      "company": "",
      "bio": "",
      "location": "Germany",
      "user_type": "User",
      "followers": 3,
      "public_repos": 13,
      "interaction_type": "star"
    },
    {
      "login": "valleefred",
      "name": "Fr\u00e9d\u00e9ric Vall\u00e9e",
      "email": "",
      "company": "",
      "bio": "",
      "location": "Auvergne",
      "user_type": "User",
      "followers": 0,
      "public_repos": 2,
      "interaction_type": "star"
    },
    {
      "login": "LennartSchu",
      "name": "Lennart",
      "email": "",
      "company": "",
      "bio": "",
      "location": "",
      "user_type": "User",
      "followers": 1,
      "public_repos": 3,
      "interaction_type": "star"
    },
    {
      "login": "sergio-dorado",
      "name": "Sergio A. Dorado-Rojas",
      "email": "",
      "company": "",
      "bio": "Researcher.",
      "location": "",
      "user_type": "User",
      "followers": 38,
      "public_repos": 9,
      "interaction_type": "star"
    },
    {
      "login": "JMorganUSU",
      "name": "Jackson Morgan",
      "email": "jackson.morgan@usu.edu",
      "company": "Utah State University",
      "bio": "Doctoral student studying electric power systems at Utah State University",
      "location": "Utah",
      "user_type": "User",
      "followers": 0,
      "public_repos": 6,
      "interaction_type": "star"
    },
    {
      "login": "xiaobao1234xiao",
      "name": "",
      "email": "",
      "company": "",
      "bio": "",
      "location": "",
      "user_type": "User",
      "followers": 0,
      "public_repos": 6,
      "interaction_type": "star"
    },
    {
      "login": "alessandranuliana",
      "name": "Alessandra Uliana",
      "email": "",
      "company": "",
      "bio": "Electrical Engineer",
      "location": "Brazil",
      "user_type": "User",
      "followers": 4,
      "public_repos": 1,
      "interaction_type": "star"
    },
    {
      "login": "FredericSabot",
      "name": "",
      "email": "",
      "company": "",
      "bio": "",
      "location": "",
      "user_type": "User",
      "followers": 1,
      "public_repos": 8,
      "interaction_type": "star"
    },
    {
      "login": "sandroni",
      "name": "",
      "email": "",
      "company": "",
      "bio": "",
      "location": "",
      "user_type": "User",
      "followers": 0,
      "public_repos": 1,
      "interaction_type": "star"
    },
    {
      "login": "mahge",
      "name": "Mahder Gebremedhin",
      "email": "",
      "company": "Open Source Modelica Consortium (OSMC)",
      "bio": "",
      "location": "Sweden",
      "user_type": "User",
      "followers": 6,
      "public_repos": 27,
      "interaction_type": "star"
    },
    {
      "login": "JosepFanals",
      "name": "Josep Fanals",
      "email": "",
      "company": "eRoots Analytics",
      "bio": "jfanals@eroots.tech",
      "location": "",
      "user_type": "User",
      "followers": 11,
      "public_repos": 5,
      "interaction_type": "star"
    },
    {
      "login": "cuzperf",
      "name": "\u9648\u667a\u9e4f",
      "email": "",
      "company": "tongyuan.cc",
      "bio": "Think twice, code once",
      "location": "\u6b66\u6c49",
      "user_type": "User",
      "followers": 5,
      "public_repos": 37,
      "interaction_type": "star"
    },
    {
      "login": "MoryNajafi",
      "name": "",
      "email": "",
      "company": "",
      "bio": "",
      "location": "",
      "user_type": "User",
      "followers": 4,
      "public_repos": 2,
      "interaction_type": "star"
    },
    {
      "login": "ekatef",
      "name": "Ekaterina",
      "email": "e.v.kasilova@gmail.com",
      "company": "",
      "bio": "",
      "location": "",
      "user_type": "User",
      "followers": 30,
      "public_repos": 56,
      "interaction_type": "star"
    },
    {
      "login": "brcortess",
      "name": "Bruno Cortes",
      "email": "",
      "company": "",
      "bio": "Engineer, Researcher, IEEE member, holding a Ph.D., M.Sc., and MBA.\r\nPast FAPESP PostDoc Fellow.",
      "location": "Brazil",
      "user_type": "User",
      "followers": 0,
      "public_repos": 0,
      "interaction_type": "star"
    },
    {
      "login": "vbwanere",
      "name": "Vaibhav Wanere",
      "email": "",
      "company": "Caterpillar Inc.",
      "bio": "Learning Precision Machining, Robotics and Industrial IoT...",
      "location": "Pontiac, IL, USA",
      "user_type": "User",
      "followers": 19,
      "public_repos": 8,
      "interaction_type": "star"
    },
    {
      "login": "jaegerstar",
      "name": "",
      "email": "",
      "company": "",
      "bio": "",
      "location": "",
      "user_type": "User",
      "followers": 6,
      "public_repos": 7,
      "interaction_type": "star"
    },
    {
      "login": "leeraiyan",
      "name": "Lee Raiyan",
      "email": "",
      "company": "",
      "bio": "",
      "location": "",
      "user_type": "User",
      "followers": 5,
      "public_repos": 35,
      "interaction_type": "star"
    },
    {
      "login": "dominikstraessle",
      "name": "Dominik Str\u00e4ssle",
      "email": "dominik8straessle@gmail.com",
      "company": "",
      "bio": "Dedicated software engineer with great interest in computer science.",
      "location": "Luzern",
      "user_type": "User",
      "followers": 27,
      "public_repos": 14,
      "interaction_type": "star"
    },
    {
      "login": "nuaawqf",
      "name": "Qifeng Wu",
      "email": "nuaawqf@gmail.com",
      "company": "Nanjing University of Aeronautics and Astronautics",
      "bio": "OpenFOAMer, CFD engineer",
      "location": "Nanjing",
      "user_type": "User",
      "followers": 0,
      "public_repos": 69,
      "interaction_type": "star"
    },
    {
      "login": "Ly0n",
      "name": "Tobias Augspurger",
      "email": "tobias.augspurger@protontypes.eu",
      "company": "@open-energy-transition @protontypes",
      "bio": "Aerospace engineer with a passion for open sustainable technology ",
      "location": "Germany, Aachen",
      "user_type": "User",
      "followers": 295,
      "public_repos": 120,
      "interaction_type": "star"
    },
    {
      "login": "martinscripts",
      "name": "Martin Franke",
      "email": "",
      "company": "",
      "bio": "",
      "location": "",
      "user_type": "User",
      "followers": 1,
      "public_repos": 5,
      "interaction_type": "star"
    },
    {
      "login": "arduinoll",
      "name": "",
      "email": "",
      "company": "",
      "bio": "",
      "location": "",
      "user_type": "User",
      "followers": 5,
      "public_repos": 0,
      "interaction_type": "star"
    },
    {
      "login": "jadeq",
      "name": "",
      "email": "",
      "company": "",
      "bio": "",
      "location": "",
      "user_type": "User",
      "followers": 0,
      "public_repos": 0,
      "interaction_type": "star"
    },
    {
      "login": "louisg-rte",
      "name": "louisg-rte",
      "email": "",
      "company": "",
      "bio": "",
      "location": "",
      "user_type": "User",
      "followers": 0,
      "public_repos": 0,
      "interaction_type": "star"
    },
    {
      "login": "lokesh-edge",
      "name": "Lokesh",
      "email": "",
      "company": "@theEdgeHq ",
      "bio": "",
      "location": "",
      "user_type": "User",
      "followers": 7,
      "public_repos": 3,
      "interaction_type": "star"
    },
    {
      "login": "sokol-a",
      "name": "Aleks Sokol",
      "email": "",
      "company": "",
      "bio": "Electrical Engineer working on Renewable Tech.",
      "location": "Europe",
      "user_type": "User",
      "followers": 0,
      "public_repos": 7,
      "interaction_type": "star"
    },
    {
      "login": "eetongsu",
      "name": "Tong Su",
      "email": "",
      "company": "",
      "bio": "",
      "location": "",
      "user_type": "User",
      "followers": 11,
      "public_repos": 5,
      "interaction_type": "star"
    },
    {
      "login": "nathaliamdc",
      "name": "Nathalia",
      "email": "",
      "company": "",
      "bio": "",
      "location": "",
      "user_type": "User",
      "followers": 5,
      "public_repos": 4,
      "interaction_type": "star"
    },
    {
      "login": "JuliusFrontzek",
      "name": "",
      "email": "",
      "company": "",
      "bio": "",
      "location": "",
      "user_type": "User",
      "followers": 6,
      "public_repos": 5,
      "interaction_type": "star"
    },
    {
      "login": "solotourist",
      "name": "",
      "email": "",
      "company": "",
      "bio": "",
      "location": "",
      "user_type": "User",
      "followers": 2,
      "public_repos": 0,
      "interaction_type": "star"
    },
    {
      "login": "karabiberym",
      "name": "Maximilian Olschewski",
      "email": "karabiberym@proton.me",
      "company": "",
      "bio": "Stand with Ukraine \ud83c\uddfa\ud83c\udde6 ",
      "location": "Germany, Karlsruhe",
      "user_type": "User",
      "followers": 31,
      "public_repos": 2,
      "interaction_type": "star"
    },
    {
      "login": "tzhang0475",
      "name": "tzhang",
      "email": "",
      "company": "",
      "bio": "",
      "location": "",
      "user_type": "User",
      "followers": 10,
      "public_repos": 8,
      "interaction_type": "star"
    },
    {
      "login": "PYF-FR",
      "name": "",
      "email": "",
      "company": "",
      "bio": "",
      "location": "",
      "user_type": "User",
      "followers": 0,
      "public_repos": 0,
      "interaction_type": "star"
    },
    {
      "login": "YitianDai",
      "name": "",
      "email": "",
      "company": "",
      "bio": "",
      "location": "",
      "user_type": "User",
      "followers": 3,
      "public_repos": 1,
      "interaction_type": "star"
    },
    {
      "login": "Aming2134",
      "name": "",
      "email": "",
      "company": "",
      "bio": "",
      "location": "",
      "user_type": "User",
      "followers": 0,
      "public_repos": 0,
      "interaction_type": "star"
    },
    {
      "login": "adriguir",
      "name": "Adrien Guironnet",
      "email": "adrien.guironnet@rte-france.com",
      "company": "RTE",
      "bio": "Animating and coordinating power system stability research efforts in RTE. Previous experience in PS simulation tool developments (notably Dynawo)",
      "location": "Paris",
      "user_type": "User",
      "followers": 8,
      "public_repos": 2,
      "interaction_type": "star"
    },
    {
      "login": "matiasCEN",
      "name": "Mat\u00edas Ag\u00fcero-Soto",
      "email": "",
      "company": "Coordinador Electrico Nacional",
      "bio": "Power System Engineer.\r\n\r\nEMT/PDT Simulation.\r\nPython, Javascript, Julia.\r\n\r\n",
      "location": "Santiago,Chile",
      "user_type": "User",
      "followers": 2,
      "public_repos": 0,
      "interaction_type": "star"
    },
    {
      "login": "ai-qui",
      "name": "",
      "email": "",
      "company": "",
      "bio": "",
      "location": "",
      "user_type": "User",
      "followers": 0,
      "public_repos": 0,
      "interaction_type": "star"
    },
    {
      "login": "KirchhoffVCR",
      "name": "",
      "email": "",
      "company": "",
      "bio": "",
      "location": "",
      "user_type": "User",
      "followers": 0,
      "public_repos": 2,
      "interaction_type": "star"
    },
    {
      "login": "phymucs",
      "name": "",
      "email": "",
      "company": "",
      "bio": "",
      "location": "",
      "user_type": "User",
      "followers": 30,
      "public_repos": 2487,
      "interaction_type": "star"
    },
    {
      "login": "HerveDavid",
      "name": "",
      "email": "",
      "company": "@rte-france",
      "bio": "",
      "location": "Lyon",
      "user_type": "User",
      "followers": 8,
      "public_repos": 31,
      "interaction_type": "star"
    },
    {
      "login": "phannebohm",
      "name": "",
      "email": "",
      "company": "",
      "bio": "",
      "location": "",
      "user_type": "User",
      "followers": 3,
      "public_repos": 17,
      "interaction_type": "star"
    },
    {
      "login": "xia-admin",
      "name": "",
      "email": "",
      "company": "",
      "bio": "",
      "location": "",
      "user_type": "User",
      "followers": 0,
      "public_repos": 1,
      "interaction_type": "star"
    },
    {
      "login": "dpaolella",
      "name": "David Paolella",
      "email": "",
      "company": "",
      "bio": "Grid Modeling at Breakthrough Energy",
      "location": "",
      "user_type": "User",
      "followers": 7,
      "public_repos": 24,
      "interaction_type": "star"
    },
    {
      "login": "KajunGambo",
      "name": "",
      "email": "",
      "company": "",
      "bio": "",
      "location": "",
      "user_type": "User",
      "followers": 1,
      "public_repos": 0,
      "interaction_type": "star"
    }
  ],
  "forkers": [
    {
      "login": "Emilie3008",
      "name": "",
      "email": "",
      "company": "",
      "bio": "",
      "location": "",
      "user_type": "User",
      "followers": 4,
      "public_repos": 4,
      "interaction_type": "fork"
    },
    {
      "login": "newall123",
      "name": "newall",
      "email": "cxqkg@foxmail.com",
      "company": "",
      "bio": "",
      "location": "",
      "user_type": "User",
      "followers": 0,
      "public_repos": 7,
      "interaction_type": "fork"
    },
    {
      "login": "casella",
      "name": "Francesco Casella",
      "email": "francesco.casella@polimi.it",
      "company": "Politecnico di Milano",
      "bio": "",
      "location": "Italy",
      "user_type": "User",
      "followers": 72,
      "public_repos": 35,
      "interaction_type": "fork"
    },
    {
      "login": "barondim",
      "name": "",
      "email": "",
      "company": "",
      "bio": "",
      "location": "",
      "user_type": "User",
      "followers": 0,
      "public_repos": 5,
      "interaction_type": "fork"
    },
    {
      "login": "apetros",
      "name": "Petros Aristidou",
      "email": "",
      "company": "",
      "bio": "Assistant Professor in Sustainable Power Systems @ Cyprus University of Technology | #Power #Energy #SmartGrid #Sustainability #EnergySecurity",
      "location": "Limassol, Cyprus",
      "user_type": "User",
      "followers": 23,
      "public_repos": 20,
      "interaction_type": "fork"
    },
    {
      "login": "martinscripts",
      "name": "Martin Franke",
      "email": "",
      "company": "",
      "bio": "",
      "location": "",
      "user_type": "User",
      "followers": 1,
      "public_repos": 5,
      "interaction_type": "fork"
    },
    {
      "login": "Diptargha",
      "name": "",
      "email": "",
      "company": "Siemens Energy",
      "bio": "",
      "location": "Manchester",
      "user_type": "User",
      "followers": 1,
      "public_repos": 10,
      "interaction_type": "fork"
    },
    {
      "login": "Adrien-Leerschool",
      "name": "",
      "email": "",
      "company": "",
      "bio": "",
      "location": "",
      "user_type": "User",
      "followers": 0,
      "public_repos": 3,
      "interaction_type": "fork"
    },
    {
      "login": "gautierbureau",
      "name": "Gautier Bureau",
      "email": "gautier.bureau@gmail.com",
      "company": "@dynawo ",
      "bio": "",
      "location": "France",
      "user_type": "User",
      "followers": 2,
      "public_repos": 37,
      "interaction_type": "fork"
    },
    {
      "login": "hubertus65",
      "name": "Hubertus Tummescheit",
      "email": "hubertus.tummescheit@gmail.com",
      "company": "Model Based Innovation LLC",
      "bio": "Dr. Hubertus Tummescheit is the Founder of Model Based Innovation LLC  and one of the founders of Modelon. He is also a board member of the Modelica Association",
      "location": "Harford, CT, USA",
      "user_type": "User",
      "followers": 11,
      "public_repos": 30,
      "interaction_type": "fork"
    },
    {
      "login": "PGimenez",
      "name": "Pere Gim\u00e9nez",
      "email": "",
      "company": "@GenieFramework ",
      "bio": "Developer and data science advocate at Genie.",
      "location": "Barcelona",
      "user_type": "User",
      "followers": 25,
      "public_repos": 38,
      "interaction_type": "fork"
    },
    {
      "login": "Saugat03",
      "name": "",
      "email": "",
      "company": "",
      "bio": "",
      "location": "",
      "user_type": "User",
      "followers": 0,
      "public_repos": 1,
      "interaction_type": "fork"
    },
    {
      "login": "jalibmon",
      "name": "",
      "email": "",
      "company": "",
      "bio": "",
      "location": "",
      "user_type": "User",
      "followers": 0,
      "public_repos": 1,
      "interaction_type": "fork"
    },
    {
      "login": "ErwanGuichard49",
      "name": "",
      "email": "",
      "company": "",
      "bio": "",
      "location": "",
      "user_type": "User",
      "followers": 0,
      "public_repos": 1,
      "interaction_type": "fork"
    },
    {
      "login": "psa2ss",
      "name": "",
      "email": "",
      "company": "",
      "bio": "",
      "location": "",
      "user_type": "User",
      "followers": 1,
      "public_repos": 43,
      "interaction_type": "fork"
    },
    {
      "login": "FredericSabot",
      "name": "",
      "email": "",
      "company": "",
      "bio": "",
      "location": "",
      "user_type": "User",
      "followers": 1,
      "public_repos": 8,
      "interaction_type": "fork"
    },
    {
      "login": "kai-zheng",
      "name": "",
      "email": "",
      "company": "",
      "bio": "",
      "location": "",
      "user_type": "User",
      "followers": 0,
      "public_repos": 67,
      "interaction_type": "fork"
    },
    {
      "login": "zamarrenolm",
      "name": "Luma",
      "email": "",
      "company": "AIA",
      "bio": "",
      "location": "Barcelona",
      "user_type": "User",
      "followers": 1,
      "public_repos": 6,
      "interaction_type": "fork"
    },
    {
      "login": "aicccode",
      "name": "aicc",
      "email": "gooqle.com.hk@gmail.com",
      "company": "aicc.site",
      "bio": "Less is more and keep it simple and stupid.",
      "location": "GZ.CN",
      "user_type": "User",
      "followers": 5,
      "public_repos": 136,
      "interaction_type": "fork"
    },
    {
      "login": "e2l-su",
      "name": "",
      "email": "",
      "company": "",
      "bio": "",
      "location": "",
      "user_type": "User",
      "followers": 0,
      "public_repos": 1,
      "interaction_type": "fork"
    },
    {
      "login": "Amrit-Gill",
      "name": "Amritbir Singh Gill",
      "email": "gill.amrit@outlook.com",
      "company": "",
      "bio": "",
      "location": "Paris, France",
      "user_type": "User",
      "followers": 1,
      "public_repos": 15,
      "interaction_type": "fork"
    },
    {
      "login": "marcosmc",
      "name": "",
      "email": "",
      "company": "",
      "bio": "",
      "location": "",
      "user_type": "User",
      "followers": 0,
      "public_repos": 1,
      "interaction_type": "fork"
    },
    {
      "login": "syedyasserali",
      "name": "syed yasser ali",
      "email": "",
      "company": "FOSSEE, IIT Bombay",
      "bio": "PROJECT RESEARCH ASSOCIATE",
      "location": "mumbai",
      "user_type": "User",
      "followers": 1,
      "public_repos": 64,
      "interaction_type": "fork"
    },
    {
      "login": "Thibaud11",
      "name": "",
      "email": "",
      "company": "",
      "bio": "",
      "location": "",
      "user_type": "User",
      "followers": 0,
      "public_repos": 6,
      "interaction_type": "fork"
    },
    {
      "login": "alirezamasoom",
      "name": "Alireza MASOOM",
      "email": "",
      "company": "\u00c9cole polytechnique de Montr\u00e9al ",
      "bio": "EMT simulation/Modelling\r\nModelica\r\nEMTP-RV\r\n",
      "location": "Montr\u00e9al ",
      "user_type": "User",
      "followers": 5,
      "public_repos": 4,
      "interaction_type": "fork"
    }
  ],
  "contributors": [
    {
      "login": "rosiereflo",
      "name": "",
      "email": "",
      "company": "",
      "bio": "",
      "location": "",
      "user_type": "User",
      "followers": 1,
      "public_repos": 0,
      "interaction_type": "contributor",
      "contributions": 640
    },
    {
      "login": "gautierbureau",
      "name": "Gautier Bureau",
      "email": "gautier.bureau@gmail.com",
      "company": "@dynawo ",
      "bio": "",
      "location": "France",
      "user_type": "User",
      "followers": 2,
      "public_repos": 37,
      "interaction_type": "contributor",
      "contributions": 432
    },
    {
      "login": "barondim",
      "name": "",
      "email": "",
      "company": "",
      "bio": "",
      "location": "",
      "user_type": "User",
      "followers": 0,
      "public_repos": 5,
      "interaction_type": "contributor",
      "contributions": 145
    },
    {
      "login": "marcochiaramello",
      "name": "",
      "email": "",
      "company": "",
      "bio": "",
      "location": "",
      "user_type": "User",
      "followers": 1,
      "public_repos": 0,
      "interaction_type": "contributor",
      "contributions": 109
    },
    {
      "login": "ErwanGuichard49",
      "name": "",
      "email": "",
      "company": "",
      "bio": "",
      "location": "",
      "user_type": "User",
      "followers": 0,
      "public_repos": 1,
      "interaction_type": "contributor",
      "contributions": 99
    },
    {
      "login": "adriguir",
      "name": "Adrien Guironnet",
      "email": "adrien.guironnet@rte-france.com",
      "company": "RTE",
      "bio": "Animating and coordinating power system stability research efforts in RTE. Previous experience in PS simulation tool developments (notably Dynawo)",
      "location": "Paris",
      "user_type": "User",
      "followers": 8,
      "public_repos": 2,
      "interaction_type": "contributor",
      "contributions": 86
    },
    {
      "login": "joyelfeghali",
      "name": "",
      "email": "",
      "company": "",
      "bio": "",
      "location": "",
      "user_type": "User",
      "followers": 0,
      "public_repos": 0,
      "interaction_type": "contributor",
      "contributions": 56
    },
    {
      "login": "valleefred",
      "name": "Fr\u00e9d\u00e9ric Vall\u00e9e",
      "email": "",
      "company": "",
      "bio": "",
      "location": "Auvergne",
      "user_type": "User",
      "followers": 0,
      "public_repos": 2,
      "interaction_type": "contributor",
      "contributions": 52
    },
    {
      "login": "RomainLosseauRTE",
      "name": "",
      "email": "",
      "company": "RTE",
      "bio": "",
      "location": "",
      "user_type": "User",
      "followers": 0,
      "public_repos": 0,
      "interaction_type": "contributor",
      "contributions": 36
    },
    {
      "login": "GerardThevenon",
      "name": "",
      "email": "",
      "company": "",
      "bio": "",
      "location": "",
      "user_type": "User",
      "followers": 0,
      "public_repos": 0,
      "interaction_type": "contributor",
      "contributions": 31
    },
    {
      "login": "jlbouchot",
      "name": "Jean-Luc Bouchot",
      "email": "",
      "company": "",
      "bio": "Math enthusiast with a taste for algorithmic development and open source projects. ",
      "location": "",
      "user_type": "User",
      "followers": 19,
      "public_repos": 15,
      "interaction_type": "contributor",
      "contributions": 29
    },
    {
      "login": "MarianneSaugierRTE",
      "name": "Marianne Saugier",
      "email": "marianne.saugier@rte-france.com",
      "company": "RTE",
      "bio": "",
      "location": "France",
      "user_type": "User",
      "followers": 1,
      "public_repos": 0,
      "interaction_type": "contributor",
      "contributions": 29
    },
    {
      "login": "gaouizer",
      "name": "",
      "email": "",
      "company": "",
      "bio": "",
      "location": "",
      "user_type": "User",
      "followers": 0,
      "public_repos": 0,
      "interaction_type": "contributor",
      "contributions": 18
    },
    {
      "login": "MarNusch",
      "name": "",
      "email": "maria.nuschke@iee.fraunhofer.de",
      "company": "Fraunhofer IEE",
      "bio": "",
      "location": "Kassel",
      "user_type": "User",
      "followers": 1,
      "public_repos": 0,
      "interaction_type": "contributor",
      "contributions": 13
    },
    {
      "login": "bongrainmat",
      "name": "",
      "email": "",
      "company": "",
      "bio": "",
      "location": "",
      "user_type": "User",
      "followers": 0,
      "public_repos": 0,
      "interaction_type": "contributor",
      "contributions": 11
    },
    {
      "login": "zamarrenolm",
      "name": "Luma",
      "email": "",
      "company": "AIA",
      "bio": "",
      "location": "Barcelona",
      "user_type": "User",
      "followers": 1,
      "public_repos": 6,
      "interaction_type": "contributor",
      "contributions": 11
    },
    {
      "login": "vermeulenthi",
      "name": "",
      "email": "",
      "company": "",
      "bio": "",
      "location": "",
      "user_type": "User",
      "followers": 1,
      "public_repos": 4,
      "interaction_type": "contributor",
      "contributions": 8
    },
    {
      "login": "cossartque",
      "name": "Quentin Cossart",
      "email": "",
      "company": "RTE",
      "bio": "",
      "location": "Paris",
      "user_type": "User",
      "followers": 1,
      "public_repos": 0,
      "interaction_type": "contributor",
      "contributions": 5
    },
    {
      "login": "thiebarrrte",
      "name": "",
      "email": "",
      "company": "",
      "bio": "",
      "location": "",
      "user_type": "User",
      "followers": 0,
      "public_repos": 0,
      "interaction_type": "contributor",
      "contributions": 5
    },
    {
      "login": "e2l-su",
      "name": "",
      "email": "",
      "company": "",
      "bio": "",
      "location": "",
      "user_type": "User",
      "followers": 0,
      "public_repos": 1,
      "interaction_type": "contributor",
      "contributions": 5
    },
    {
      "login": "martinscripts",
      "name": "Martin Franke",
      "email": "",
      "company": "",
      "bio": "",
      "location": "",
      "user_type": "User",
      "followers": 1,
      "public_repos": 5,
      "interaction_type": "contributor",
      "contributions": 4
    },
    {
      "login": "AlexPoiron",
      "name": "Alex Poiron",
      "email": "",
      "company": "",
      "bio": "",
      "location": "",
      "user_type": "User",
      "followers": 0,
      "public_repos": 11,
      "interaction_type": "contributor",
      "contributions": 3
    },
    {
      "login": "deslooverejul",
      "name": "",
      "email": "",
      "company": "",
      "bio": "",
      "location": "",
      "user_type": "User",
      "followers": 0,
      "public_repos": 0,
      "interaction_type": "contributor",
      "contributions": 3
    },
    {
      "login": "Philibert92",
      "name": "",
      "email": "",
      "company": "",
      "bio": "",
      "location": "",
      "user_type": "User",
      "followers": 1,
      "public_repos": 0,
      "interaction_type": "contributor",
      "contributions": 3
    },
    {
      "login": "goasguenerw",
      "name": "Erwann GOASGUEN",
      "email": "",
      "company": "",
      "bio": "",
      "location": "",
      "user_type": "User",
      "followers": 0,
      "public_repos": 0,
      "interaction_type": "contributor",
      "contributions": 3
    },
    {
      "login": "RonanMarache",
      "name": "Ronan Marache",
      "email": "",
      "company": "",
      "bio": "",
      "location": "",
      "user_type": "User",
      "followers": 0,
      "public_repos": 0,
      "interaction_type": "contributor",
      "contributions": 2
    },
    {
      "login": "louisg-rte",
      "name": "louisg-rte",
      "email": "",
      "company": "",
      "bio": "",
      "location": "",
      "user_type": "User",
      "followers": 0,
      "public_repos": 0,
      "interaction_type": "contributor",
      "contributions": 2
    },
    {
      "login": "SoerenLohr",
      "name": "S\u00f6ren Lohr",
      "email": "",
      "company": "Fraunhofer IEE",
      "bio": "Email: soeren.lohr@iee.fraunhofer.de",
      "location": "",
      "user_type": "User",
      "followers": 1,
      "public_repos": 0,
      "interaction_type": "contributor",
      "contributions": 1
    },
    {
      "login": "mehdirte",
      "name": "mehdikarmani",
      "email": "",
      "company": "",
      "bio": "",
      "location": "",
      "user_type": "User",
      "followers": 0,
      "public_repos": 0,
      "interaction_type": "contributor",
      "contributions": 1
    }
  ],
  "watchers": [
    {
      "login": "rosiereflo",
      "name": "",
      "email": "",
      "company": "",
      "bio": "",
      "location": "",
      "user_type": "User",
      "followers": 1,
      "public_repos": 0,
      "interaction_type": "watcher"
    },
    {
      "login": "MarianneSaugierRTE",
      "name": "Marianne Saugier",
      "email": "marianne.saugier@rte-france.com",
      "company": "RTE",
      "bio": "",
      "location": "France",
      "user_type": "User",
      "followers": 1,
      "public_repos": 0,
      "interaction_type": "watcher"
    },
    {
      "login": "petitrenaudseb",
      "name": "",
      "email": "",
      "company": "",
      "bio": "",
      "location": "",
      "user_type": "User",
      "followers": 0,
      "public_repos": 1,
      "interaction_type": "watcher"
    },
    {
      "login": "serge-inmost",
      "name": "Simon Gesret",
      "email": "",
      "company": "@Boralex-France ",
      "bio": "",
      "location": "Lyon, France",
      "user_type": "User",
      "followers": 3,
      "public_repos": 5,
      "interaction_type": "watcher"
    },
    {
      "login": "cuihantao",
      "name": "Hantao Cui",
      "email": "",
      "company": "North Carolina State University",
      "bio": "Associate Professor of Electrical and Computer Engineering. \r\n\r\nWe are bridging the power systems community with scientific computing.",
      "location": "Raleigh, NC",
      "user_type": "User",
      "followers": 242,
      "public_repos": 195,
      "interaction_type": "watcher"
    },
    {
      "login": "Neirda8282",
      "name": "",
      "email": "",
      "company": "",
      "bio": "",
      "location": "",
      "user_type": "User",
      "followers": 1,
      "public_repos": 30,
      "interaction_type": "watcher"
    },
    {
      "login": "rwl",
      "name": "Richard Lincoln",
      "email": "r.w.lincoln@gmail.com",
      "company": "",
      "bio": "Power Engineer",
      "location": "Berlin",
      "user_type": "User",
      "followers": 179,
      "public_repos": 186,
      "interaction_type": "watcher"
    },
    {
      "login": "milton-alvarenga",
      "name": "",
      "email": "",
      "company": "",
      "bio": "",
      "location": "",
      "user_type": "User",
      "followers": 30,
      "public_repos": 24,
      "interaction_type": "watcher"
    },
    {
      "login": "Oprax",
      "name": "Romain Muller",
      "email": "",
      "company": "",
      "bio": "",
      "location": "",
      "user_type": "User",
      "followers": 8,
      "public_repos": 27,
      "interaction_type": "watcher"
    },
    {
      "login": "RomainLosseauRTE",
      "name": "",
      "email": "",
      "company": "RTE",
      "bio": "",
      "location": "",
      "user_type": "User",
      "followers": 0,
      "public_repos": 0,
      "interaction_type": "watcher"
    },
    {
      "login": "whoiszyc",
      "name": "Yichen Zhang",
      "email": "",
      "company": "The University of Texas at Arlington",
      "bio": "Assistant Professor\r\nThe University of Texas at Arlington\r\nArlington, TX 76010, USA",
      "location": "416 Yates Street, Arlington, TX 76010, USA",
      "user_type": "User",
      "followers": 56,
      "public_repos": 98,
      "interaction_type": "watcher"
    },
    {
      "login": "pphuth",
      "name": "Philipp Huth",
      "email": "",
      "company": "",
      "bio": "",
      "location": "Germany",
      "user_type": "User",
      "followers": 46,
      "public_repos": 22,
      "interaction_type": "watcher"
    },
    {
      "login": "cybfr",
      "name": "",
      "email": "",
      "company": "",
      "bio": "",
      "location": "",
      "user_type": "User",
      "followers": 1,
      "public_repos": 23,
      "interaction_type": "watcher"
    },
    {
      "login": "syedyasserali",
      "name": "syed yasser ali",
      "email": "",
      "company": "FOSSEE, IIT Bombay",
      "bio": "PROJECT RESEARCH ASSOCIATE",
      "location": "mumbai",
      "user_type": "User",
      "followers": 1,
      "public_repos": 64,
      "interaction_type": "watcher"
    },
    {
      "login": "rsegur",
      "name": "Roman",
      "email": "",
      "company": "SuperGrid institute",
      "bio": "",
      "location": "Lyon",
      "user_type": "User",
      "followers": 1,
      "public_repos": 0,
      "interaction_type": "watcher"
    },
    {
      "login": "e2l-su",
      "name": "",
      "email": "",
      "company": "",
      "bio": "",
      "location": "",
      "user_type": "User",
      "followers": 0,
      "public_repos": 1,
      "interaction_type": "watcher"
    },
    {
      "login": "Sciemon",
      "name": "",
      "email": "",
      "company": "Fraunhofer IEE",
      "bio": "",
      "location": "Kassel, Germany",
      "user_type": "User",
      "followers": 6,
      "public_repos": 6,
      "interaction_type": "watcher"
    },
    {
      "login": "BDonnot",
      "name": "Benjamin DONNOT",
      "email": "",
      "company": "",
      "bio": "",
      "location": "",
      "user_type": "User",
      "followers": 50,
      "public_repos": 31,
      "interaction_type": "watcher"
    },
    {
      "login": "renonat",
      "name": "Reno Natalizio",
      "email": "",
      "company": "Opus One Solutions",
      "bio": "",
      "location": "Canada",
      "user_type": "User",
      "followers": 6,
      "public_repos": 5,
      "interaction_type": "watcher"
    },
    {
      "login": "songshaofeng",
      "name": "",
      "email": "",
      "company": "",
      "bio": "",
      "location": "",
      "user_type": "User",
      "followers": 0,
      "public_repos": 6,
      "interaction_type": "watcher"
    },
    {
      "login": "aicccode",
      "name": "aicc",
      "email": "gooqle.com.hk@gmail.com",
      "company": "aicc.site",
      "bio": "Less is more and keep it simple and stupid.",
      "location": "GZ.CN",
      "user_type": "User",
      "followers": 5,
      "public_repos": 136,
      "interaction_type": "watcher"
    },
    {
      "login": "piliadis",
      "name": "",
      "email": "",
      "company": "",
      "bio": "",
      "location": "",
      "user_type": "User",
      "followers": 1,
      "public_repos": 1,
      "interaction_type": "watcher"
    },
    {
      "login": "sorrento",
      "name": "",
      "email": "",
      "company": "",
      "bio": "",
      "location": "",
      "user_type": "User",
      "followers": 0,
      "public_repos": 27,
      "interaction_type": "watcher"
    },
    {
      "login": "metab0t",
      "name": "Yue Yang",
      "email": "",
      "company": "Hefei University of Technology",
      "bio": "Academic researcher interested in \r\noptimization of power system",
      "location": "China",
      "user_type": "User",
      "followers": 80,
      "public_repos": 64,
      "interaction_type": "watcher"
    },
    {
      "login": "lucassm",
      "name": "Lucas Melo",
      "email": "lucas.silveiramelo@gmail.com",
      "company": "Federal University of Ceara",
      "bio": "Associate Professor at Electrical Engineering Department - Federal University of Ceara - Brazil",
      "location": "Fortaleza, Ce - Brazil",
      "user_type": "User",
      "followers": 46,
      "public_repos": 63,
      "interaction_type": "watcher"
    },
    {
      "login": "traversaro",
      "name": "Silvio Traversaro",
      "email": "",
      "company": "Italian Institute of Technology",
      "bio": "If you mentioned me and I did not reply in the last 72h, probably I lost the message somehow, so please ping me, thanks!\r\n",
      "location": "Genoa",
      "user_type": "User",
      "followers": 467,
      "public_repos": 762,
      "interaction_type": "watcher"
    },
    {
      "login": "thorade",
      "name": "Matthis Thorade",
      "email": "matthis.thorade@modelon.com",
      "company": "@modelon",
      "bio": "",
      "location": "",
      "user_type": "User",
      "followers": 61,
      "public_repos": 14,
      "interaction_type": "watcher"
    },
    {
      "login": "GGiraudG",
      "name": "Guillaume",
      "email": "",
      "company": "@RTE",
      "bio": "",
      "location": "",
      "user_type": "User",
      "followers": 0,
      "public_repos": 0,
      "interaction_type": "watcher"
    },
    {
      "login": "gautierbureau",
      "name": "Gautier Bureau",
      "email": "gautier.bureau@gmail.com",
      "company": "@dynawo ",
      "bio": "",
      "location": "France",
      "user_type": "User",
      "followers": 2,
      "public_repos": 37,
      "interaction_type": "watcher"
    },
    {
      "login": "yayima",
      "name": "Edward Zhang",
      "email": "",
      "company": "",
      "bio": "",
      "location": "Beijing",
      "user_type": "User",
      "followers": 18,
      "public_repos": 12,
      "interaction_type": "watcher"
    },
    {
      "login": "sylvlecl",
      "name": "Sylvain Leclerc",
      "email": "sylvain.leclerc@rte-france.com",
      "company": "RTE",
      "bio": "Software engineer at RTE, with a strong interest in energy sector, computations, and applied mathematics.",
      "location": "Paris",
      "user_type": "User",
      "followers": 5,
      "public_repos": 5,
      "interaction_type": "watcher"
    },
    {
      "login": "MV564",
      "name": "Jose Martin",
      "email": "",
      "company": "IIUNAM",
      "bio": "PhD Candidate at Institute of Engineering, UNAM",
      "location": "Mexico",
      "user_type": "User",
      "followers": 0,
      "public_repos": 0,
      "interaction_type": "watcher"
    },
    {
      "login": "gnakti",
      "name": "",
      "email": "",
      "company": "",
      "bio": "",
      "location": "",
      "user_type": "User",
      "followers": 3,
      "public_repos": 5,
      "interaction_type": "watcher"
    },
    {
      "login": "MachinesOnTheRise",
      "name": "RiseOfTheMachines",
      "email": "",
      "company": "",
      "bio": "",
      "location": "Austin, Tx",
      "user_type": "User",
      "followers": 0,
      "public_repos": 0,
      "interaction_type": "watcher"
    },
    {
      "login": "sifatron",
      "name": "Sifat Shahriar Khan",
      "email": "sifat.torque@gmail.com",
      "company": "EnerSys",
      "bio": "AI and Machine Learning Lead at EnerSys | Experienced Embedded Firmware Developer",
      "location": "Reading, PA",
      "user_type": "User",
      "followers": 4,
      "public_repos": 66,
      "interaction_type": "watcher"
    },
    {
      "login": "jiedxu",
      "name": "Jie (Edward) Xu",
      "email": "edxu96@outlook.com",
      "company": "House of Energy Markets and Finance, University Duisburg-Essen",
      "bio": "Math simulation/optimization, graph theory and dynamic procurement & pricing for energy systems, food supplies, retailing, etc.",
      "location": "Essen, Germany",
      "user_type": "User",
      "followers": 94,
      "public_repos": 20,
      "interaction_type": "watcher"
    },
    {
      "login": "BenoitJeanson",
      "name": "Beno\u00eet Jeanson",
      "email": "",
      "company": "RTE",
      "bio": "",
      "location": "Paris",
      "user_type": "User",
      "followers": 0,
      "public_repos": 10,
      "interaction_type": "watcher"
    },
    {
      "login": "martinmoraga",
      "name": "Martin Moraga",
      "email": "",
      "company": "",
      "bio": "",
      "location": "Germany",
      "user_type": "User",
      "followers": 3,
      "public_repos": 13,
      "interaction_type": "watcher"
    },
    {
      "login": "valleefred",
      "name": "Fr\u00e9d\u00e9ric Vall\u00e9e",
      "email": "",
      "company": "",
      "bio": "",
      "location": "Auvergne",
      "user_type": "User",
      "followers": 0,
      "public_repos": 2,
      "interaction_type": "watcher"
    },
    {
      "login": "LennartSchu",
      "name": "Lennart",
      "email": "",
      "company": "",
      "bio": "",
      "location": "",
      "user_type": "User",
      "followers": 1,
      "public_repos": 3,
      "interaction_type": "watcher"
    },
    {
      "login": "sergio-dorado",
      "name": "Sergio A. Dorado-Rojas",
      "email": "",
      "company": "",
      "bio": "Researcher.",
      "location": "",
      "user_type": "User",
      "followers": 38,
      "public_repos": 9,
      "interaction_type": "watcher"
    },
    {
      "login": "JMorganUSU",
      "name": "Jackson Morgan",
      "email": "jackson.morgan@usu.edu",
      "company": "Utah State University",
      "bio": "Doctoral student studying electric power systems at Utah State University",
      "location": "Utah",
      "user_type": "User",
      "followers": 0,
      "public_repos": 6,
      "interaction_type": "watcher"
    },
    {
      "login": "xiaobao1234xiao",
      "name": "",
      "email": "",
      "company": "",
      "bio": "",
      "location": "",
      "user_type": "User",
      "followers": 0,
      "public_repos": 6,
      "interaction_type": "watcher"
    },
    {
      "login": "alessandranuliana",
      "name": "Alessandra Uliana",
      "email": "",
      "company": "",
      "bio": "Electrical Engineer",
      "location": "Brazil",
      "user_type": "User",
      "followers": 4,
      "public_repos": 1,
      "interaction_type": "watcher"
    },
    {
      "login": "FredericSabot",
      "name": "",
      "email": "",
      "company": "",
      "bio": "",
      "location": "",
      "user_type": "User",
      "followers": 1,
      "public_repos": 8,
      "interaction_type": "watcher"
    },
    {
      "login": "sandroni",
      "name": "",
      "email": "",
      "company": "",
      "bio": "",
      "location": "",
      "user_type": "User",
      "followers": 0,
      "public_repos": 1,
      "interaction_type": "watcher"
    },
    {
      "login": "mahge",
      "name": "Mahder Gebremedhin",
      "email": "",
      "company": "Open Source Modelica Consortium (OSMC)",
      "bio": "",
      "location": "Sweden",
      "user_type": "User",
      "followers": 6,
      "public_repos": 27,
      "interaction_type": "watcher"
    },
    {
      "login": "JosepFanals",
      "name": "Josep Fanals",
      "email": "",
      "company": "eRoots Analytics",
      "bio": "jfanals@eroots.tech",
      "location": "",
      "user_type": "User",
      "followers": 11,
      "public_repos": 5,
      "interaction_type": "watcher"
    },
    {
      "login": "cuzperf",
      "name": "\u9648\u667a\u9e4f",
      "email": "",
      "company": "tongyuan.cc",
      "bio": "Think twice, code once",
      "location": "\u6b66\u6c49",
      "user_type": "User",
      "followers": 5,
      "public_repos": 37,
      "interaction_type": "watcher"
    },
    {
      "login": "MoryNajafi",
      "name": "",
      "email": "",
      "company": "",
      "bio": "",
      "location": "",
      "user_type": "User",
      "followers": 4,
      "public_repos": 2,
      "interaction_type": "watcher"
    },
    {
      "login": "ekatef",
      "name": "Ekaterina",
      "email": "e.v.kasilova@gmail.com",
      "company": "",
      "bio": "",
      "location": "",
      "user_type": "User",
      "followers": 30,
      "public_repos": 56,
      "interaction_type": "watcher"
    },
    {
      "login": "brcortess",
      "name": "Bruno Cortes",
      "email": "",
      "company": "",
      "bio": "Engineer, Researcher, IEEE member, holding a Ph.D., M.Sc., and MBA.\r\nPast FAPESP PostDoc Fellow.",
      "location": "Brazil",
      "user_type": "User",
      "followers": 0,
      "public_repos": 0,
      "interaction_type": "watcher"
    },
    {
      "login": "vbwanere",
      "name": "Vaibhav Wanere",
      "email": "",
      "company": "Caterpillar Inc.",
      "bio": "Learning Precision Machining, Robotics and Industrial IoT...",
      "location": "Pontiac, IL, USA",
      "user_type": "User",
      "followers": 19,
      "public_repos": 8,
      "interaction_type": "watcher"
    },
    {
      "login": "jaegerstar",
      "name": "",
      "email": "",
      "company": "",
      "bio": "",
      "location": "",
      "user_type": "User",
      "followers": 6,
      "public_repos": 7,
      "interaction_type": "watcher"
    },
    {
      "login": "leeraiyan",
      "name": "Lee Raiyan",
      "email": "",
      "company": "",
      "bio": "",
      "location": "",
      "user_type": "User",
      "followers": 5,
      "public_repos": 35,
      "interaction_type": "watcher"
    },
    {
      "login": "dominikstraessle",
      "name": "Dominik Str\u00e4ssle",
      "email": "dominik8straessle@gmail.com",
      "company": "",
      "bio": "Dedicated software engineer with great interest in computer science.",
      "location": "Luzern",
      "user_type": "User",
      "followers": 27,
      "public_repos": 14,
      "interaction_type": "watcher"
    },
    {
      "login": "nuaawqf",
      "name": "Qifeng Wu",
      "email": "nuaawqf@gmail.com",
      "company": "Nanjing University of Aeronautics and Astronautics",
      "bio": "OpenFOAMer, CFD engineer",
      "location": "Nanjing",
      "user_type": "User",
      "followers": 0,
      "public_repos": 69,
      "interaction_type": "watcher"
    },
    {
      "login": "Ly0n",
      "name": "Tobias Augspurger",
      "email": "tobias.augspurger@protontypes.eu",
      "company": "@open-energy-transition @protontypes",
      "bio": "Aerospace engineer with a passion for open sustainable technology ",
      "location": "Germany, Aachen",
      "user_type": "User",
      "followers": 295,
      "public_repos": 120,
      "interaction_type": "watcher"
    },
    {
      "login": "martinscripts",
      "name": "Martin Franke",
      "email": "",
      "company": "",
      "bio": "",
      "location": "",
      "user_type": "User",
      "followers": 1,
      "public_repos": 5,
      "interaction_type": "watcher"
    },
    {
      "login": "arduinoll",
      "name": "",
      "email": "",
      "company": "",
      "bio": "",
      "location": "",
      "user_type": "User",
      "followers": 5,
      "public_repos": 0,
      "interaction_type": "watcher"
    },
    {
      "login": "jadeq",
      "name": "",
      "email": "",
      "company": "",
      "bio": "",
      "location": "",
      "user_type": "User",
      "followers": 0,
      "public_repos": 0,
      "interaction_type": "watcher"
    },
    {
      "login": "louisg-rte",
      "name": "louisg-rte",
      "email": "",
      "company": "",
      "bio": "",
      "location": "",
      "user_type": "User",
      "followers": 0,
      "public_repos": 0,
      "interaction_type": "watcher"
    },
    {
      "login": "lokesh-edge",
      "name": "Lokesh",
      "email": "",
      "company": "@theEdgeHq ",
      "bio": "",
      "location": "",
      "user_type": "User",
      "followers": 7,
      "public_repos": 3,
      "interaction_type": "watcher"
    },
    {
      "login": "sokol-a",
      "name": "Aleks Sokol",
      "email": "",
      "company": "",
      "bio": "Electrical Engineer working on Renewable Tech.",
      "location": "Europe",
      "user_type": "User",
      "followers": 0,
      "public_repos": 7,
      "interaction_type": "watcher"
    },
    {
      "login": "eetongsu",
      "name": "Tong Su",
      "email": "",
      "company": "",
      "bio": "",
      "location": "",
      "user_type": "User",
      "followers": 11,
      "public_repos": 5,
      "interaction_type": "watcher"
    },
    {
      "login": "nathaliamdc",
      "name": "Nathalia",
      "email": "",
      "company": "",
      "bio": "",
      "location": "",
      "user_type": "User",
      "followers": 5,
      "public_repos": 4,
      "interaction_type": "watcher"
    },
    {
      "login": "JuliusFrontzek",
      "name": "",
      "email": "",
      "company": "",
      "bio": "",
      "location": "",
      "user_type": "User",
      "followers": 6,
      "public_repos": 5,
      "interaction_type": "watcher"
    },
    {
      "login": "solotourist",
      "name": "",
      "email": "",
      "company": "",
      "bio": "",
      "location": "",
      "user_type": "User",
      "followers": 2,
      "public_repos": 0,
      "interaction_type": "watcher"
    },
    {
      "login": "karabiberym",
      "name": "Maximilian Olschewski",
      "email": "karabiberym@proton.me",
      "company": "",
      "bio": "Stand with Ukraine \ud83c\uddfa\ud83c\udde6 ",
      "location": "Germany, Karlsruhe",
      "user_type": "User",
      "followers": 31,
      "public_repos": 2,
      "interaction_type": "watcher"
    },
    {
      "login": "tzhang0475",
      "name": "tzhang",
      "email": "",
      "company": "",
      "bio": "",
      "location": "",
      "user_type": "User",
      "followers": 10,
      "public_repos": 8,
      "interaction_type": "watcher"
    },
    {
      "login": "PYF-FR",
      "name": "",
      "email": "",
      "company": "",
      "bio": "",
      "location": "",
      "user_type": "User",
      "followers": 0,
      "public_repos": 0,
      "interaction_type": "watcher"
    },
    {
      "login": "YitianDai",
      "name": "",
      "email": "",
      "company": "",
      "bio": "",
      "location": "",
      "user_type": "User",
      "followers": 3,
      "public_repos": 1,
      "interaction_type": "watcher"
    },
    {
      "login": "Aming2134",
      "name": "",
      "email": "",
      "company": "",
      "bio": "",
      "location": "",
      "user_type": "User",
      "followers": 0,
      "public_repos": 0,
      "interaction_type": "watcher"
    },
    {
      "login": "adriguir",
      "name": "Adrien Guironnet",
      "email": "adrien.guironnet@rte-france.com",
      "company": "RTE",
      "bio": "Animating and coordinating power system stability research efforts in RTE. Previous experience in PS simulation tool developments (notably Dynawo)",
      "location": "Paris",
      "user_type": "User",
      "followers": 8,
      "public_repos": 2,
      "interaction_type": "watcher"
    },
    {
      "login": "matiasCEN",
      "name": "Mat\u00edas Ag\u00fcero-Soto",
      "email": "",
      "company": "Coordinador Electrico Nacional",
      "bio": "Power System Engineer.\r\n\r\nEMT/PDT Simulation.\r\nPython, Javascript, Julia.\r\n\r\n",
      "location": "Santiago,Chile",
      "user_type": "User",
      "followers": 2,
      "public_repos": 0,
      "interaction_type": "watcher"
    },
    {
      "login": "ai-qui",
      "name": "",
      "email": "",
      "company": "",
      "bio": "",
      "location": "",
      "user_type": "User",
      "followers": 0,
      "public_repos": 0,
      "interaction_type": "watcher"
    },
    {
      "login": "KirchhoffVCR",
      "name": "",
      "email": "",
      "company": "",
      "bio": "",
      "location": "",
      "user_type": "User",
      "followers": 0,
      "public_repos": 2,
      "interaction_type": "watcher"
    },
    {
      "login": "phymucs",
      "name": "",
      "email": "",
      "company": "",
      "bio": "",
      "location": "",
      "user_type": "User",
      "followers": 30,
      "public_repos": 2487,
      "interaction_type": "watcher"
    },
    {
      "login": "HerveDavid",
      "name": "",
      "email": "",
      "company": "@rte-france",
      "bio": "",
      "location": "Lyon",
      "user_type": "User",
      "followers": 8,
      "public_repos": 31,
      "interaction_type": "watcher"
    },
    {
      "login": "phannebohm",
      "name": "",
      "email": "",
      "company": "",
      "bio": "",
      "location": "",
      "user_type": "User",
      "followers": 3,
      "public_repos": 17,
      "interaction_type": "watcher"
    },
    {
      "login": "xia-admin",
      "name": "",
      "email": "",
      "company": "",
      "bio": "",
      "location": "",
      "user_type": "User",
      "followers": 0,
      "public_repos": 1,
      "interaction_type": "watcher"
    },
    {
      "login": "dpaolella",
      "name": "David Paolella",
      "email": "",
      "company": "",
      "bio": "Grid Modeling at Breakthrough Energy",
      "location": "",
      "user_type": "User",
      "followers": 7,
      "public_repos": 24,
      "interaction_type": "watcher"
    },
    {
      "login": "KajunGambo",
      "name": "",
      "email": "",
      "company": "",
      "bio": "",
      "location": "",
      "user_type": "User",
      "followers": 1,
      "public_repos": 0,
      "interaction_type": "watcher"
    }
  ]
}